{
    "children": {
        "0": {
            "children": {"0": {
                "children": {"0": {
                    "children": {
                        "0": {
                            "id": "224",
                            "type": "receiveGo"
                        },
                        "1": {
                            "children": {
                                "0": {"type": "literal"},
                                "1": {
                                    "type": "literal",
                                    "value": "2"
                                }
                            },
                            "childrenOrder": [
                                "0",
                                "1"
                            ],
                            "id": "241",
                            "type": "doSayFor"
                        },
                        "2": {
                            "children": {"0": {"type": "literal"}},
                            "childrenOrder": ["0"],
                            "id": "259",
                            "type": "doAsk"
                        },
                        "3": {
                            "children": {
                                "0": {
                                    "children": {"0": {
                                        "children": {
                                            "0": {"type": "literal"},
                                            "1": {
                                                "id": "439",
                                                "type": "getLastAnswer"
                                            }
                                        },
                                        "childrenOrder": [
                                            "0",
                                            "1"
                                        ],
                                        "type": "list"
                                    }},
                                    "childrenOrder": ["0"],
                                    "id": "438",
                                    "type": "reportJoinWords"
                                },
                                "1": {
                                    "type": "literal",
                                    "value": "2"
                                }
                            },
                            "childrenOrder": [
                                "0",
                                "1"
                            ],
                            "id": "384",
                            "type": "doSayFor"
                        },
                        "4": {
                            "children": {
                                "0": {
                                    "type": "varMenu",
                                    "value": "number"
                                },
                                "1": {
                                    "children": {
                                        "0": {
                                            "type": "literal",
                                            "value": "1"
                                        },
                                        "1": {
                                            "type": "literal",
                                            "value": "10"
                                        }
                                    },
                                    "childrenOrder": [
                                        "0",
                                        "1"
                                    ],
                                    "id": "423",
                                    "type": "reportRandom"
                                }
                            },
                            "childrenOrder": [
                                "0",
                                "1"
                            ],
                            "id": "394",
                            "type": "doSetVar"
                        },
                        "5": {
                            "children": {"0": {"type": "literal"}},
                            "childrenOrder": ["0"],
                            "id": "476",
                            "type": "doAsk"
                        },
                        "6": {
                            "children": {
                                "0": {
                                    "children": {
                                        "0": {
                                            "id": "475",
                                            "type": "getLastAnswer"
                                        },
                                        "1": {
                                            "id": "474",
                                            "type": "var",
                                            "value": "number"
                                        }
                                    },
                                    "childrenOrder": [
                                        "0",
                                        "1"
                                    ],
                                    "id": "473",
                                    "type": "reportEquals"
                                },
                                "1": {
                                    "children": {"0": {
                                        "children": {
                                            "0": {
                                                "children": {
                                                    "0": {
                                                        "id": "480",
                                                        "type": "getLastAnswer"
                                                    },
                                                    "1": {
                                                        "id": "479",
                                                        "type": "var",
                                                        "value": "number"
                                                    }
                                                },
                                                "childrenOrder": [
                                                    "0",
                                                    "1"
                                                ],
                                                "id": "478",
                                                "type": "reportEquals"
                                            },
                                            "1": {
                                                "children": {"0": {
                                                    "children": {
                                                        "0": {"type": "literal"},
                                                        "1": {
                                                            "type": "literal",
                                                            "value": "2"
                                                        }
                                                    },
                                                    "childrenOrder": [
                                                        "0",
                                                        "1"
                                                    ],
                                                    "id": "483",
                                                    "type": "doSayFor"
                                                }},
                                                "childrenOrder": ["0"],
                                                "type": "script"
                                            },
                                            "2": {
                                                "children": {
                                                    "0": {
                                                        "children": {
                                                            "0": {
                                                                "children": {
                                                                    "0": {
                                                                        "id": "492",
                                                                        "type": "getLastAnswer"
                                                                    },
                                                                    "1": {
                                                                        "id": "490",
                                                                        "type": "var",
                                                                        "value": "number"
                                                                    }
                                                                },
                                                                "childrenOrder": [
                                                                    "0",
                                                                    "1"
                                                                ],
                                                                "id": "488",
                                                                "type": "reportLessThan"
                                                            },
                                                            "1": {
                                                                "children": {
                                                                    "0": {
                                                                        "children": {
                                                                            "0": {"type": "literal"},
                                                                            "1": {
                                                                                "type": "literal",
                                                                                "value": "3"
                                                                            }
                                                                        },
                                                                        "childrenOrder": [
                                                                            "0",
                                                                            "1"
                                                                        ],
                                                                        "id": "498",
                                                                        "type": "doSayFor"
                                                                    },
                                                                    "1": {"type": "doAsk"}
                                                                },
                                                                "childrenOrder": [
                                                                    "0",
                                                                    "1"
                                                                ],
                                                                "type": "script"
                                                            }
                                                        },
                                                        "childrenOrder": [
                                                            "0",
                                                            "1"
                                                        ],
                                                        "id": "484",
                                                        "type": "doIf"
                                                    },
                                                    "1": {
                                                        "children": {
                                                            "0": {
                                                                "children": {
                                                                    "0": {
                                                                        "id": "489",
                                                                        "type": "var",
                                                                        "value": "number"
                                                                    },
                                                                    "1": {
                                                                        "id": "491",
                                                                        "type": "getLastAnswer"
                                                                    }
                                                                },
                                                                "childrenOrder": [
                                                                    "0",
                                                                    "1"
                                                                ],
                                                                "id": "486",
                                                                "type": "reportLessThan"
                                                            },
                                                            "1": {
                                                                "children": {"0": {
                                                                    "children": {
                                                                        "0": {"type": "literal"},
                                                                        "1": {
                                                                            "type": "literal",
                                                                            "value": "3"
                                                                        }
                                                                    },
                                                                    "childrenOrder": [
                                                                        "0",
                                                                        "1"
                                                                    ],
                                                                    "id": "497",
                                                                    "type": "doSayFor"
                                                                }},
                                                                "childrenOrder": ["0"],
                                                                "type": "script"
                                                            }
                                                        },
                                                        "childrenOrder": [
                                                            "0",
                                                            "1"
                                                        ],
                                                        "id": "485",
                                                        "type": "doIf"
                                                    }
                                                },
                                                "childrenOrder": [
                                                    "0",
                                                    "1"
                                                ],
                                                "type": "script"
                                            }
                                        },
                                        "childrenOrder": [
                                            "0",
                                            "1",
                                            "2"
                                        ],
                                        "id": "477",
                                        "type": "doIfElse"
                                    }},
                                    "childrenOrder": ["0"],
                                    "type": "script"
                                }
                            },
                            "childrenOrder": [
                                "0",
                                "1"
                            ],
                            "id": "472",
                            "type": "doUntil"
                        }
                    },
                    "childrenOrder": [
                        "0",
                        "1",
                        "2",
                        "3",
                        "4",
                        "5",
                        "6"
                    ],
                    "type": "script"
                }},
                "childrenOrder": ["0"],
                "id": "Sprite",
                "type": "sprite",
                "value": "Sprite"
            }},
            "childrenOrder": ["0"],
            "id": "stage",
            "type": "stage",
            "value": "Stage"
        },
        "1": {
            "children": {
                "0": {"type": "script"},
                "1": {
                    "type": "varDec",
                    "value": "hello"
                },
                "2": {
                    "type": "varDec",
                    "value": "name"
                }
            },
            "childrenOrder": [
                "0",
                "1",
                "2"
            ],
            "id": "1d1ff6f7-baaf-4f0c-86e1-21f06ca63157",
            "type": "customBlock",
            "value": "say %s %s"
        },
        "2": {
            "type": "varDec",
            "value": "number"
        }
    },
    "childrenOrder": [
        "0",
        "1",
        "2"
    ],
    "id": "5e3badb4-0a26-4167-b3c6-c270604d38df",
    "type": "Snap!shot",
    "error": 0.050582395331152434
}