{
    "children": {
        "0": {
            "children": {"0": {
                "children": {"0": {
                    "children": {
                        "0": {
                            "id": "469",
                            "type": "receiveGo"
                        },
                        "1": {
                            "children": {
                                "0": {"type": "literal"},
                                "1": {
                                    "type": "literal",
                                    "value": "2"
                                }
                            },
                            "childrenOrder": [
                                "0",
                                "1"
                            ],
                            "id": "470",
                            "type": "doSayFor"
                        },
                        "2": {
                            "children": {"0": {"type": "literal"}},
                            "childrenOrder": ["0"],
                            "id": "471",
                            "type": "doAsk"
                        },
                        "3": {
                            "children": {
                                "0": {
                                    "children": {"0": {
                                        "children": {
                                            "0": {"type": "literal"},
                                            "1": {
                                                "id": "474",
                                                "type": "getLastAnswer"
                                            }
                                        },
                                        "childrenOrder": [
                                            "0",
                                            "1"
                                        ],
                                        "type": "list"
                                    }},
                                    "childrenOrder": ["0"],
                                    "id": "473",
                                    "type": "reportJoinWords"
                                },
                                "1": {
                                    "type": "literal",
                                    "value": "2"
                                }
                            },
                            "childrenOrder": [
                                "0",
                                "1"
                            ],
                            "id": "472",
                            "type": "doSayFor"
                        },
                        "4": {
                            "children": {
                                "0": {
                                    "type": "varMenu",
                                    "value": "correct answer"
                                },
                                "1": {
                                    "children": {
                                        "0": {
                                            "type": "literal",
                                            "value": "1"
                                        },
                                        "1": {
                                            "type": "literal",
                                            "value": "10"
                                        }
                                    },
                                    "childrenOrder": [
                                        "0",
                                        "1"
                                    ],
                                    "id": "475",
                                    "type": "reportRandom"
                                }
                            },
                            "childrenOrder": [
                                "0",
                                "1"
                            ],
                            "id": "492",
                            "type": "doSetVar"
                        },
                        "5": {
                            "children": {
                                "0": {
                                    "children": {
                                        "0": {
                                            "id": "553",
                                            "type": "getLastAnswer"
                                        },
                                        "1": {
                                            "id": "554",
                                            "type": "var",
                                            "value": "correct answer"
                                        }
                                    },
                                    "childrenOrder": [
                                        "0",
                                        "1"
                                    ],
                                    "id": "552",
                                    "type": "reportEquals"
                                },
                                "1": {
                                    "children": {
                                        "0": {
                                            "children": {"0": {"type": "literal"}},
                                            "childrenOrder": ["0"],
                                            "id": "536",
                                            "type": "doAsk"
                                        },
                                        "1": {
                                            "children": {
                                                "0": {
                                                    "children": {
                                                        "0": {
                                                            "id": "540",
                                                            "type": "getLastAnswer"
                                                        },
                                                        "1": {
                                                            "id": "541",
                                                            "type": "var",
                                                            "value": "correct answer"
                                                        }
                                                    },
                                                    "childrenOrder": [
                                                        "0",
                                                        "1"
                                                    ],
                                                    "id": "539",
                                                    "type": "reportEquals"
                                                },
                                                "1": {
                                                    "children": {"0": {
                                                        "children": {
                                                            "0": {"type": "literal"},
                                                            "1": {
                                                                "type": "literal",
                                                                "value": "2"
                                                            }
                                                        },
                                                        "childrenOrder": [
                                                            "0",
                                                            "1"
                                                        ],
                                                        "id": "542",
                                                        "type": "doSayFor"
                                                    }},
                                                    "childrenOrder": ["0"],
                                                    "type": "script"
                                                },
                                                "2": {
                                                    "children": {"0": {
                                                        "children": {
                                                            "0": {"type": "literal"},
                                                            "1": {
                                                                "type": "literal",
                                                                "value": "2"
                                                            }
                                                        },
                                                        "childrenOrder": [
                                                            "0",
                                                            "1"
                                                        ],
                                                        "id": "543",
                                                        "type": "doSayFor"
                                                    }},
                                                    "childrenOrder": ["0"],
                                                    "type": "script"
                                                }
                                            },
                                            "childrenOrder": [
                                                "0",
                                                "1",
                                                "2"
                                            ],
                                            "id": "538",
                                            "type": "doIfElse"
                                        }
                                    },
                                    "childrenOrder": [
                                        "0",
                                        "1"
                                    ],
                                    "type": "script"
                                }
                            },
                            "childrenOrder": [
                                "0",
                                "1"
                            ],
                            "id": "551",
                            "type": "doUntil"
                        }
                    },
                    "childrenOrder": [
                        "0",
                        "1",
                        "2",
                        "3",
                        "4",
                        "5"
                    ],
                    "type": "script"
                }},
                "childrenOrder": ["0"],
                "id": "Sprite",
                "type": "sprite",
                "value": "Sprite"
            }},
            "childrenOrder": ["0"],
            "id": "stage",
            "type": "stage",
            "value": "Stage"
        },
        "1": {
            "type": "varDec",
            "value": "correct answer"
        },
        "2": {
            "type": "varDec",
            "value": "length"
        }
    },
    "childrenOrder": [
        "0",
        "1",
        "2"
    ],
    "id": "dfb44912-61eb-48ab-a9d3-0f3781d63f36",
    "type": "Snap!shot",
    "error": 0.047460467855368005
}